[
    {
        "categorie": "",
        "name": "[System Process]",
        "pid": [
            {
                "checked": false,
                "numeroPid": 0
            }
        ]
    },
    {
        "categorie": "",
        "name": "System",
        "pid": [
            {
                "checked": false,
                "numeroPid": 4
            }
        ]
    },
    {
        "categorie": "",
        "name": "Secure System",
        "pid": [
            {
                "checked": false,
                "numeroPid": 56
            }
        ]
    },
    {
        "categorie": "",
        "name": "Registry",
        "pid": [
            {
                "checked": false,
                "numeroPid": 108
            }
        ]
    },
    {
        "categorie": "",
        "name": "smss.exe",
        "pid": [
            {
                "checked": false,
                "numeroPid": 596
            }
        ]
    },
    {
        "categorie": "",
        "name": "csrss.exe",
        "pid": [
            {
                "checked": false,
                "numeroPid": 696
            },
            {
                "checked": false,
                "numeroPid": 824
            }
        ]
    },
    {
        "categorie": "",
        "name": "wininit.exe",
        "pid": [
            {
                "checked": false,
                "numeroPid": 804
            }
        ]
    },
    {
        "categorie": "",
        "name": "services.exe",
        "pid": [
            {
                "checked": false,
                "numeroPid": 880
            }
        ]
    },
    {
        "categorie": "",
        "name": "LsaIso.exe",
        "pid": [
            {
                "checked": false,
                "numeroPid": 900
            }
        ]
    },
    {
        "categorie": "",
        "name": "lsass.exe",
        "pid": [
            {
                "checked": false,
                "numeroPid": 908
            }
        ]
    },
    {
        "categorie": "",
        "name": "winlogon.exe",
        "pid": [
            {
                "checked": false,
                "numeroPid": 984
            }
        ]
    },
    {
        "categorie": "",
        "name": "svchost.exe",
        "pid": [
            {
                "checked": false,
                "numeroPid": 800
            },
            {
                "checked": false,
                "numeroPid": 1104
            },
            {
                "checked": false,
                "numeroPid": 1180
            },
            {
                "checked": false,
                "numeroPid": 1284
            },
            {
                "checked": false,
                "numeroPid": 1312
            },
            {
                "checked": false,
                "numeroPid": 1360
            },
            {
                "checked": false,
                "numeroPid": 1372
            },
            {
                "checked": false,
                "numeroPid": 1392
            },
            {
                "checked": false,
                "numeroPid": 1492
            },
            {
                "checked": false,
                "numeroPid": 1552
            },
            {
                "checked": false,
                "numeroPid": 1668
            },
            {
                "checked": false,
                "numeroPid": 1812
            },
            {
                "checked": false,
                "numeroPid": 1828
            },
            {
                "checked": false,
                "numeroPid": 1848
            },
            {
                "checked": false,
                "numeroPid": 1872
            },
            {
                "checked": false,
                "numeroPid": 1908
            },
            {
                "checked": false,
                "numeroPid": 2012
            },
            {
                "checked": false,
                "numeroPid": 2028
            },
            {
                "checked": false,
                "numeroPid": 2124
            },
            {
                "checked": false,
                "numeroPid": 2132
            },
            {
                "checked": false,
                "numeroPid": 2320
            },
            {
                "checked": false,
                "numeroPid": 2504
            },
            {
                "checked": false,
                "numeroPid": 2572
            },
            {
                "checked": false,
                "numeroPid": 2616
            },
            {
                "checked": false,
                "numeroPid": 2824
            },
            {
                "checked": false,
                "numeroPid": 2860
            },
            {
                "checked": false,
                "numeroPid": 2880
            },
            {
                "checked": false,
                "numeroPid": 2888
            },
            {
                "checked": false,
                "numeroPid": 2916
            },
            {
                "checked": false,
                "numeroPid": 2996
            },
            {
                "checked": false,
                "numeroPid": 3108
            },
            {
                "checked": false,
                "numeroPid": 3116
            },
            {
                "checked": false,
                "numeroPid": 3148
            },
            {
                "checked": false,
                "numeroPid": 3160
            },
            {
                "checked": false,
                "numeroPid": 3300
            },
            {
                "checked": false,
                "numeroPid": 3340
            },
            {
                "checked": false,
                "numeroPid": 3372
            },
            {
                "checked": false,
                "numeroPid": 3508
            },
            {
                "checked": false,
                "numeroPid": 3564
            },
            {
                "checked": false,
                "numeroPid": 3592
            },
            {
                "checked": false,
                "numeroPid": 3800
            },
            {
                "checked": false,
                "numeroPid": 3964
            },
            {
                "checked": false,
                "numeroPid": 4048
            },
            {
                "checked": false,
                "numeroPid": 4056
            },
            {
                "checked": false,
                "numeroPid": 4136
            },
            {
                "checked": false,
                "numeroPid": 4180
            },
            {
                "checked": false,
                "numeroPid": 4536
            },
            {
                "checked": false,
                "numeroPid": 4596
            },
            {
                "checked": false,
                "numeroPid": 4612
            },
            {
                "checked": false,
                "numeroPid": 4628
            },
            {
                "checked": false,
                "numeroPid": 4756
            },
            {
                "checked": false,
                "numeroPid": 4856
            },
            {
                "checked": false,
                "numeroPid": 4956
            },
            {
                "checked": false,
                "numeroPid": 4992
            },
            {
                "checked": false,
                "numeroPid": 5080
            },
            {
                "checked": false,
                "numeroPid": 5188
            },
            {
                "checked": false,
                "numeroPid": 5352
            },
            {
                "checked": false,
                "numeroPid": 5556
            },
            {
                "checked": false,
                "numeroPid": 2436
            },
            {
                "checked": false,
                "numeroPid": 7044
            },
            {
                "checked": false,
                "numeroPid": 7116
            },
            {
                "checked": false,
                "numeroPid": 7600
            },
            {
                "checked": false,
                "numeroPid": 7608
            },
            {
                "checked": false,
                "numeroPid": 7660
            },
            {
                "checked": false,
                "numeroPid": 7872
            },
            {
                "checked": false,
                "numeroPid": 7932
            },
            {
                "checked": false,
                "numeroPid": 8032
            },
            {
                "checked": false,
                "numeroPid": 7284
            },
            {
                "checked": false,
                "numeroPid": 7944
            },
            {
                "checked": false,
                "numeroPid": 8000
            },
            {
                "checked": false,
                "numeroPid": 6140
            },
            {
                "checked": false,
                "numeroPid": 8488
            },
            {
                "checked": false,
                "numeroPid": 8620
            },
            {
                "checked": false,
                "numeroPid": 8420
            },
            {
                "checked": false,
                "numeroPid": 12736
            },
            {
                "checked": false,
                "numeroPid": 8480
            },
            {
                "checked": false,
                "numeroPid": 10992
            },
            {
                "checked": false,
                "numeroPid": 2868
            },
            {
                "checked": false,
                "numeroPid": 12832
            },
            {
                "checked": false,
                "numeroPid": 7672
            },
            {
                "checked": false,
                "numeroPid": 404
            },
            {
                "checked": false,
                "numeroPid": 1952
            },
            {
                "checked": false,
                "numeroPid": 8824
            }
        ]
    },
    {
        "categorie": "",
        "name": "fontdrvhost.exe",
        "pid": [
            {
                "checked": false,
                "numeroPid": 920
            },
            {
                "checked": false,
                "numeroPid": 936
            }
        ]
    },
    {
        "categorie": "",
        "name": "WUDFHost.exe",
        "pid": [
            {
                "checked": false,
                "numeroPid": 1132
            }
        ]
    },
    {
        "categorie": "",
        "name": "dwm.exe",
        "pid": [
            {
                "checked": false,
                "numeroPid": 1428
            }
        ]
    },
    {
        "categorie": "",
        "name": "IntelCpHDCPSvc.exe",
        "pid": [
            {
                "checked": false,
                "numeroPid": 1764
            }
        ]
    },
    {
        "categorie": "",
        "name": "IntelCpHeciSvc.exe",
        "pid": [
            {
                "checked": false,
                "numeroPid": 2112
            }
        ]
    },
    {
        "categorie": "",
        "name": "Memory Compression",
        "pid": [
            {
                "checked": false,
                "numeroPid": 3028
            }
        ]
    },
    {
        "categorie": "",
        "name": "igfxCUIService.exe",
        "pid": [
            {
                "checked": false,
                "numeroPid": 3056
            }
        ]
    },
    {
        "categorie": "",
        "name": "RtkAudioService64.exe",
        "pid": [
            {
                "checked": false,
                "numeroPid": 3720
            }
        ]
    },
    {
        "categorie": "",
        "name": "RAVBg64.exe",
        "pid": [
            {
                "checked": false,
                "numeroPid": 3888
            },
            {
                "checked": false,
                "numeroPid": 3904
            },
            {
                "checked": false,
                "numeroPid": 11412
            }
        ]
    },
    {
        "categorie": "",
        "name": "unsecapp.exe",
        "pid": [
            {
                "checked": false,
                "numeroPid": 3824
            }
        ]
    },
    {
        "categorie": "",
        "name": "WmiPrvSE.exe",
        "pid": [
            {
                "checked": false,
                "numeroPid": 4156
            },
            {
                "checked": false,
                "numeroPid": 5324
            }
        ]
    },
    {
        "categorie": "",
        "name": "wlanext.exe",
        "pid": [
            {
                "checked": false,
                "numeroPid": 4368
            }
        ]
    },
    {
        "categorie": "",
        "name": "spoolsv.exe",
        "pid": [
            {
                "checked": false,
                "numeroPid": 4388
            }
        ]
    },
    {
        "categorie": "",
        "name": "conhost.exe",
        "pid": [
            {
                "checked": false,
                "numeroPid": 4412
            },
            {
                "checked": false,
                "numeroPid": 8816
            },
            {
                "checked": false,
                "numeroPid": 9028
            },
            {
                "checked": false,
                "numeroPid": 1408
            },
            {
                "checked": false,
                "numeroPid": 6148
            }
        ]
    },
    {
        "categorie": "",
        "name": "HidMonitorSvc.exe",
        "pid": [
            {
                "checked": false,
                "numeroPid": 4604
            }
        ]
    },
    {
        "categorie": "",
        "name": "warp-svc.exe",
        "pid": [
            {
                "checked": false,
                "numeroPid": 4620
            }
        ]
    },
    {
        "categorie": "",
        "name": "OneApp.IGCC.WinService.exe",
        "pid": [
            {
                "checked": false,
                "numeroPid": 4712
            }
        ]
    },
    {
        "categorie": "",
        "name": "IpOverUsbSvc.exe",
        "pid": [
            {
                "checked": false,
                "numeroPid": 4792
            }
        ]
    },
    {
        "categorie": "",
        "name": "LMS.exe",
        "pid": [
            {
                "checked": false,
                "numeroPid": 4804
            }
        ]
    },
    {
        "categorie": "",
        "name": "esif_uf.exe",
        "pid": [
            {
                "checked": false,
                "numeroPid": 4812
            }
        ]
    },
    {
        "categorie": "",
        "name": "MpDefenderCoreService.exe",
        "pid": [
            {
                "checked": false,
                "numeroPid": 4864
            }
        ]
    },
    {
        "categorie": "",
        "name": "gamingservices.exe",
        "pid": [
            {
                "checked": false,
                "numeroPid": 4888
            }
        ]
    },
    {
        "categorie": "",
        "name": "RstMwService.exe",
        "pid": [
            {
                "checked": false,
                "numeroPid": 4912
            }
        ]
    },
    {
        "categorie": "",
        "name": "MsMpEng.exe",
        "pid": [
            {
                "checked": false,
                "numeroPid": 4432
            }
        ]
    },
    {
        "categorie": "",
        "name": "WavesSysSvc64.exe",
        "pid": [
            {
                "checked": false,
                "numeroPid": 4556
            }
        ]
    },
    {
        "categorie": "",
        "name": "wslservice.exe",
        "pid": [
            {
                "checked": false,
                "numeroPid": 4176
            }
        ]
    },
    {
        "categorie": "",
        "name": "gamingservicesnet.exe",
        "pid": [
            {
                "checked": false,
                "numeroPid": 5132
            }
        ]
    },
    {
        "categorie": "",
        "name": "WMIRegistrationService.exe",
        "pid": [
            {
                "checked": false,
                "numeroPid": 5172
            }
        ]
    },
    {
        "categorie": "",
        "name": "jhi_service.exe",
        "pid": [
            {
                "checked": false,
                "numeroPid": 5256
            }
        ]
    },
    {
        "categorie": "",
        "name": "SearchIndexer.exe",
        "pid": [
            {
                "checked": false,
                "numeroPid": 5876
            }
        ]
    },
    {
        "categorie": "",
        "name": "dllhost.exe",
        "pid": [
            {
                "checked": false,
                "numeroPid": 6724
            },
            {
                "checked": false,
                "numeroPid": 11520
            }
        ]
    },
    {
        "categorie": "",
        "name": "AggregatorHost.exe",
        "pid": [
            {
                "checked": false,
                "numeroPid": 6956
            }
        ]
    },
    {
        "categorie": "",
        "name": "MoUsoCoreWorker.exe",
        "pid": [
            {
                "checked": false,
                "numeroPid": 6476
            }
        ]
    },
    {
        "categorie": "",
        "name": "Apoint.exe",
        "pid": [
            {
                "checked": false,
                "numeroPid": 7388
            }
        ]
    },
    {
        "categorie": "",
        "name": "sihost.exe",
        "pid": [
            {
                "checked": false,
                "numeroPid": 7560
            }
        ]
    },
    {
        "categorie": "",
        "name": "PresentationFontCache.exe",
        "pid": [
            {
                "checked": false,
                "numeroPid": 7700
            }
        ]
    },
    {
        "categorie": "",
        "name": "taskhostw.exe",
        "pid": [
            {
                "checked": false,
                "numeroPid": 7804
            },
            {
                "checked": false,
                "numeroPid": 10016
            }
        ]
    },
    {
        "categorie": "",
        "name": "ctfmon.exe",
        "pid": [
            {
                "checked": false,
                "numeroPid": 8124
            }
        ]
    },
    {
        "categorie": "",
        "name": "igfxEM.exe",
        "pid": [
            {
                "checked": false,
                "numeroPid": 7192
            }
        ]
    },
    {
        "categorie": "",
        "name": "ApMsgFwd.exe",
        "pid": [
            {
                "checked": false,
                "numeroPid": 4480
            }
        ]
    },
    {
        "categorie": "",
        "name": "explorer.exe",
        "pid": [
            {
                "checked": false,
                "numeroPid": 6104
            }
        ]
    },
    {
        "categorie": "",
        "name": "ApRemote.exe",
        "pid": [
            {
                "checked": false,
                "numeroPid": 8324
            }
        ]
    },
    {
        "categorie": "",
        "name": "hidfind.exe",
        "pid": [
            {
                "checked": false,
                "numeroPid": 8332
            }
        ]
    },
    {
        "categorie": "",
        "name": "ApntEx.exe",
        "pid": [
            {
                "checked": false,
                "numeroPid": 8584
            }
        ]
    },
    {
        "categorie": "",
        "name": "StartMenuExperienceHost.exe",
        "pid": [
            {
                "checked": false,
                "numeroPid": 9468
            }
        ]
    },
    {
        "categorie": "",
        "name": "RuntimeBroker.exe",
        "pid": [
            {
                "checked": false,
                "numeroPid": 9552
            },
            {
                "checked": false,
                "numeroPid": 9860
            },
            {
                "checked": false,
                "numeroPid": 10136
            },
            {
                "checked": false,
                "numeroPid": 11032
            },
            {
                "checked": false,
                "numeroPid": 13228
            },
            {
                "checked": false,
                "numeroPid": 7276
            }
        ]
    },
    {
        "categorie": "",
        "name": "SearchApp.exe",
        "pid": [
            {
                "checked": false,
                "numeroPid": 9676
            }
        ]
    },
    {
        "categorie": "",
        "name": "NisSrv.exe",
        "pid": [
            {
                "checked": false,
                "numeroPid": 9344
            }
        ]
    },
    {
        "categorie": "",
        "name": "SecurityHealthSystray.exe",
        "pid": [
            {
                "checked": false,
                "numeroPid": 11188
            }
        ]
    },
    {
        "categorie": "",
        "name": "SecurityHealthService.exe",
        "pid": [
            {
                "checked": false,
                "numeroPid": 11200
            }
        ]
    },
    {
        "categorie": "",
        "name": "RtkNGUI64.exe",
        "pid": [
            {
                "checked": false,
                "numeroPid": 10364
            }
        ]
    },
    {
        "categorie": "",
        "name": "ShellExperienceHost.exe",
        "pid": [
            {
                "checked": false,
                "numeroPid": 11172
            }
        ]
    },
    {
        "categorie": "",
        "name": "WavesSvc64.exe",
        "pid": [
            {
                "checked": false,
                "numeroPid": 11628
            }
        ]
    },
    {
        "categorie": "",
        "name": "vgtray.exe",
        "pid": [
            {
                "checked": false,
                "numeroPid": 12128
            }
        ]
    },
    {
        "categorie": "",
        "name": "Microsoft.SharePoint.exe",
        "pid": [
            {
                "checked": false,
                "numeroPid": 12180
            }
        ]
    },
    {
        "categorie": "Browser",
        "name": "msedge.exe",
        "pid": [
            {
                "checked": false,
                "numeroPid": 11396
            },
            {
                "checked": false,
                "numeroPid": 10592
            },
            {
                "checked": false,
                "numeroPid": 11120
            },
            {
                "checked": false,
                "numeroPid": 11552
            },
            {
                "checked": false,
                "numeroPid": 11696
            },
            {
                "checked": false,
                "numeroPid": 11428
            },
            {
                "checked": false,
                "numeroPid": 12636
            }
        ]
    },
    {
        "categorie": "",
        "name": "Cloudflare WARP.exe",
        "pid": [
            {
                "checked": false,
                "numeroPid": 700
            }
        ]
    },
    {
        "categorie": "",
        "name": "jusched.exe",
        "pid": [
            {
                "checked": false,
                "numeroPid": 11404
            }
        ]
    },
    {
        "categorie": "",
        "name": "SystemSettings.exe",
        "pid": [
            {
                "checked": false,
                "numeroPid": 1932
            }
        ]
    },
    {
        "categorie": "",
        "name": "ApplicationFrameHost.exe",
        "pid": [
            {
                "checked": false,
                "numeroPid": 7420
            }
        ]
    },
    {
        "categorie": "",
        "name": "UserOOBEBroker.exe",
        "pid": [
            {
                "checked": false,
                "numeroPid": 10752
            }
        ]
    },
    {
        "categorie": "Browser",
        "name": "firefox.exe",
        "pid": [
            {
                "checked": false,
                "numeroPid": 7212
            },
            {
                "checked": false,
                "numeroPid": 9924
            },
            {
                "checked": false,
                "numeroPid": 8664
            },
            {
                "checked": false,
                "numeroPid": 12236
            },
            {
                "checked": false,
                "numeroPid": 13044
            },
            {
                "checked": false,
                "numeroPid": 13028
            },
            {
                "checked": false,
                "numeroPid": 5340
            },
            {
                "checked": false,
                "numeroPid": 5304
            },
            {
                "checked": false,
                "numeroPid": 5344
            },
            {
                "checked": false,
                "numeroPid": 9632
            },
            {
                "checked": false,
                "numeroPid": 4972
            },
            {
                "checked": false,
                "numeroPid": 12480
            },
            {
                "checked": false,
                "numeroPid": 4652
            },
            {
                "checked": false,
                "numeroPid": 5924
            },
            {
                "checked": false,
                "numeroPid": 9136
            },
            {
                "checked": false,
                "numeroPid": 2744
            }
        ]
    },
    {
        "categorie": "",
        "name": "Video.UI.exe",
        "pid": [
            {
                "checked": false,
                "numeroPid": 5684
            }
        ]
    },
    {
        "categorie": "",
        "name": "TextInputHost.exe",
        "pid": [
            {
                "checked": false,
                "numeroPid": 1904
            }
        ]
    },
    {
        "categorie": "",
        "name": "CalculatorApp.exe",
        "pid": [
            {
                "checked": false,
                "numeroPid": 11664
            }
        ]
    },
    {
        "categorie": "",
        "name": "SgrmBroker.exe",
        "pid": [
            {
                "checked": false,
                "numeroPid": 10784
            }
        ]
    },
    {
        "categorie": "",
        "name": "git-bash.exe",
        "pid": [
            {
                "checked": false,
                "numeroPid": 12648
            }
        ]
    },
    {
        "categorie": "",
        "name": "mintty.exe",
        "pid": [
            {
                "checked": false,
                "numeroPid": 1692
            }
        ]
    },
    {
        "categorie": "",
        "name": "bash.exe",
        "pid": [
            {
                "checked": false,
                "numeroPid": 8252
            }
        ]
    },
    {
        "categorie": "",
        "name": "Code.exe",
        "pid": [
            {
                "checked": false,
                "numeroPid": 2472
            },
            {
                "checked": false,
                "numeroPid": 3276
            },
            {
                "checked": false,
                "numeroPid": 10536
            },
            {
                "checked": false,
                "numeroPid": 7492
            },
            {
                "checked": false,
                "numeroPid": 9024
            },
            {
                "checked": false,
                "numeroPid": 8064
            },
            {
                "checked": false,
                "numeroPid": 12716
            },
            {
                "checked": false,
                "numeroPid": 11212
            },
            {
                "checked": false,
                "numeroPid": 12272
            },
            {
                "checked": false,
                "numeroPid": 10000
            }
        ]
    },
    {
        "categorie": "",
        "name": "devenv.exe",
        "pid": [
            {
                "checked": false,
                "numeroPid": 10024
            }
        ]
    },
    {
        "categorie": "",
        "name": "PerfWatson2.exe",
        "pid": [
            {
                "checked": false,
                "numeroPid": 11452
            }
        ]
    },
    {
        "categorie": "",
        "name": "Microsoft.ServiceHub.Controller.exe",
        "pid": [
            {
                "checked": false,
                "numeroPid": 12528
            }
        ]
    },
    {
        "categorie": "",
        "name": "ServiceHub.VSDetouredHost.exe",
        "pid": [
            {
                "checked": false,
                "numeroPid": 12604
            }
        ]
    },
    {
        "categorie": "",
        "name": "ServiceHub.ThreadedWaitDialog.exe",
        "pid": [
            {
                "checked": false,
                "numeroPid": 7204
            }
        ]
    },
    {
        "categorie": "",
        "name": "ServiceHub.IndexingService.exe",
        "pid": [
            {
                "checked": false,
                "numeroPid": 2876
            }
        ]
    },
    {
        "categorie": "",
        "name": "ServiceHub.IdentityHost.exe",
        "pid": [
            {
                "checked": false,
                "numeroPid": 12728
            }
        ]
    },
    {
        "categorie": "",
        "name": "ServiceHub.IntellicodeModelService.exe",
        "pid": [
            {
                "checked": false,
                "numeroPid": 12696
            }
        ]
    },
    {
        "categorie": "",
        "name": "MSBuild.exe",
        "pid": [
            {
                "checked": false,
                "numeroPid": 9936
            }
        ]
    },
    {
        "categorie": "",
        "name": "vctip.exe",
        "pid": [
            {
                "checked": false,
                "numeroPid": 7008
            }
        ]
    },
    {
        "categorie": "",
        "name": "smartscreen.exe",
        "pid": [
            {
                "checked": false,
                "numeroPid": 4204
            }
        ]
    },
    {
        "categorie": "",
        "name": "vite-server.exe",
        "pid": [
            {
                "checked": false,
                "numeroPid": 2784
            },
            {
                "checked": false,
                "numeroPid": 2008
            }
        ]
    },
    {
        "categorie": "",
        "name": "cmd.exe",
        "pid": [
            {
                "checked": false,
                "numeroPid": 7328
            },
            {
                "checked": false,
                "numeroPid": 1648
            },
            {
                "checked": false,
                "numeroPid": 9184
            },
            {
                "checked": false,
                "numeroPid": 3728
            }
        ]
    },
    {
        "categorie": "",
        "name": "node.exe",
        "pid": [
            {
                "checked": false,
                "numeroPid": 7300
            },
            {
                "checked": false,
                "numeroPid": 2912
            }
        ]
    },
    {
        "categorie": "",
        "name": "esbuild.exe",
        "pid": [
            {
                "checked": false,
                "numeroPid": 11740
            }
        ]
    },
    {
        "categorie": "",
        "name": "PIDRecup.exe",
        "pid": [
            {
                "checked": false,
                "numeroPid": 9620
            }
        ]
    }
]